django_pinba-1.3.0.dist-info/DESCRIPTION.rst
django_pinba-1.3.0.dist-info/METADATA
django_pinba-1.3.0.dist-info/metadata.json
django_pinba-1.3.0.dist-info/RECORD
django_pinba-1.3.0.dist-info/top_level.txt
django_pinba-1.3.0.dist-info/WHEEL
pinba/__init__.py
pinba/defaults.py
pinba/middleware.py
pinba/monitor.py
pinba/timers.py
