Metadata-Version: 2.0
Name: django-pinba
Version: 1.3.0
Summary: django pinba
Home-page: http://github.com/gotlium/django-pinba
Author: GoTLiuM InSPiRiT
Author-email: gotlium@gmail.com
License: UNKNOWN
Keywords: django pinba
Platform: UNKNOWN
Classifier: Development Status :: 5 - Production/Stable
Classifier: Environment :: Web Environment
Classifier: Framework :: Django
Classifier: Intended Audience :: Developers
Classifier: License :: OSI Approved :: GNU General Public License (GPL)
Classifier: Operating System :: OS Independent
Classifier: Programming Language :: Python
Requires-Dist: pynba (==0.5.4)
